schema_automator/__init__.py
schema_automator/annotators/__init__.py
schema_automator/annotators/curated_to_enums.py
schema_automator/annotators/enum_annotator.py
schema_automator/annotators/enums_to_curateable.py
schema_automator/annotators/jsonld_annotator.py
schema_automator/annotators/llm_annotator.py
schema_automator/annotators/schema_annotator.py
schema_automator/cli.py
schema_automator/generalizers/__init__.py
schema_automator/generalizers/csv_data_generalizer.py
schema_automator/generalizers/generalizer.py
schema_automator/generalizers/infer_model_from_rdftab.py
schema_automator/generalizers/json_instance_generalizer.py
schema_automator/generalizers/pandas_generalizer.py
schema_automator/generalizers/rdf_data_generalizer.py
schema_automator/generalizers/toml_instance_generalizer.py
schema_automator/importers/__init__.py
schema_automator/importers/cadsr_import_engine.py
schema_automator/importers/dbml_import_engine.py
schema_automator/importers/dosdp_import_engine.py
schema_automator/importers/frictionless_import_engine.py
schema_automator/importers/import_engine.py
schema_automator/importers/jsonschema_import_engine.py
schema_automator/importers/kwalify_import_engine.py
schema_automator/importers/owl_import_engine.py
schema_automator/importers/rdfs_import_engine.py
schema_automator/importers/sql_import_engine.py
schema_automator/importers/tabular_import_engine.py
schema_automator/jsonschema/__init__.py
schema_automator/metamodels/__init__.py
schema_automator/metamodels/cadsr.py
schema_automator/metamodels/cadsr.yaml
schema_automator/metamodels/dosdp/__init__.py
schema_automator/metamodels/dosdp/dosdp_linkml.yaml
schema_automator/metamodels/dosdp/model.py
schema_automator/metamodels/frictionless.py
schema_automator/metamodels/frictionless.yaml
schema_automator/metamodels/jsonschema.py
schema_automator/utils/__init__.py
schema_automator/utils/enums_pvs_tsv.py
schema_automator/utils/instance_extractor.py
schema_automator/utils/schema_extractor.py
schema_automator-0.5.3.dist-info/LICENSE
schema_automator-0.5.3.dist-info/METADATA
schema_automator-0.5.3.dist-info/WHEEL
schema_automator-0.5.3.dist-info/entry_points.txt
schema_automator-0.5.3.dist-info/RECORD
