Metadata-Version: 2.3
Name: schema_automator
Version: 0.5.3
Summary: Infer models, enrich with meaning for terms including enum permissible values
License: BSD 3-Clause
Keywords: schema,linked data,data modeling,rdf,owl
Author: Chris Mungall
Requires-Python: >=3.9,<4.0
Classifier: Development Status :: 5 - Production/Stable
Classifier: Environment :: Console
Classifier: Intended Audience :: Developers
Classifier: Intended Audience :: Healthcare Industry
Classifier: Intended Audience :: Science/Research
Classifier: License :: OSI Approved :: BSD License
Classifier: License :: Other/Proprietary License
Classifier: Operating System :: OS Independent
Classifier: Programming Language :: Python
Classifier: Programming Language :: Python :: 3
Classifier: Programming Language :: Python :: 3.9
Classifier: Programming Language :: Python :: 3.10
Classifier: Programming Language :: Python :: 3.11
Classifier: Programming Language :: Python :: 3.12
Classifier: Programming Language :: Python :: 3.13
Provides-Extra: docs
Provides-Extra: mariadb
Requires-Dist: click-default-group (>=1.2.4,<2.0.0)
Requires-Dist: click-log (>=0.4.0)
Requires-Dist: duckdb (>=0.10.1,<0.11.0)
Requires-Dist: funowl (>=0.2.3)
Requires-Dist: inflect (>=6.0.0)
Requires-Dist: jsonpatch (>=1.32)
Requires-Dist: linkml (>=1.7.4,<2.0.0)
Requires-Dist: linkml-runtime (>=1.7.2,<2.0.0)
Requires-Dist: mkdocs (>=1.2.3)
Requires-Dist: numpy (<2.0)
Requires-Dist: oaklib (>=0.5.25)
Requires-Dist: pandas (>=1.3.5)
Requires-Dist: pandera (>=0.12.0)
Requires-Dist: psycopg2-binary (>=2.9.2,<3.0.0)
Requires-Dist: pydbml (>=1.1.2,<2.0.0)
Requires-Dist: python-dateutil (>=2.8.2)
Requires-Dist: quantulum3 (>=0.7.9)
Requires-Dist: requests (>=2.26.0)
Requires-Dist: schemasheets (>=0.1.24)
Requires-Dist: strsimpy (>=0.2.1)
Requires-Dist: tomlkit (>=0.11.4)
Requires-Dist: xmltodict (>=0.13.0,<0.14.0)
Project-URL: Documentation, https://linkml.io/schema-automator/
Project-URL: Repository, https://github.com/linkml/schema-automator/
